iconoclast-3.2.0.dist-info/METADATA
iconoclast-3.2.0.dist-info/WHEEL
iconoclast-3.2.0.dist-info/entry_points.txt
iconoclast-3.2.0.dist-info/licenses/LICENSE.md
iconoclast/__init__.py
iconoclast/cli/__init__.py
iconoclast/cli/cli.py
iconoclast/cli/context.py
iconoclast/cli/exceptions.py
iconoclast/cli/graphql/__init__.py
iconoclast/cli/graphql/schema.py
iconoclast/cli/iconokit/iconokit/__init__.py
iconoclast/cli/iconokit/pyproject.toml
iconoclast/cli/prompts.py
iconoclast/plugins/__init__.py
iconoclast/plugins/cards.py
iconoclast/plugins/main.py
iconoclast/plugins/utils.py
iconoclast-3.2.0.dist-info/RECORD
