Metadata-Version: 2.1
Name: iconoclast
Version: 3.2.0
Summary: Font Awesome Pro integration for Material for MkDocs
Author-Email: celsius narhwal <hello@celsiusnarhwal.dev>
Requires-Python: >=3.8
Requires-Dist: decorator>=5.1.1
Requires-Dist: dict-deep>=4.1.2
Requires-Dist: halo>=0.0.31
Requires-Dist: importlib-metadata>=8.5.0
Requires-Dist: inquirerpy>=0.3.4
Requires-Dist: merge-args>=0.1.5
Requires-Dist: mkdocs>=1.6.1
Requires-Dist: path>=16.16.0
Requires-Dist: semver>=3.0.2
Requires-Dist: sgqlc>=16.4
Requires-Dist: typer>=0.13.1
Requires-Dist: yarl>=1.15.2
